python_serviceplatformen/__init__.py
python_serviceplatformen/authentication.py
python_serviceplatformen/date_helper.py
python_serviceplatformen/digital_post.py
python_serviceplatformen/message_broker.py
python_serviceplatformen/models/__init__.py
python_serviceplatformen/models/message.py
python_serviceplatformen/models/xml_util.py
python_serviceplatformen-3.1.0.dist-info/licenses/LICENSE
python_serviceplatformen-3.1.0.dist-info/METADATA
python_serviceplatformen-3.1.0.dist-info/WHEEL
python_serviceplatformen-3.1.0.dist-info/top_level.txt
python_serviceplatformen-3.1.0.dist-info/RECORD
