Metadata-Version: 2.4
Name: python_serviceplatformen
Version: 3.1.0
Summary: Python modules for easier use of Kombit's serviceplatformen.
Author-email: ITK Development <itk-rpa@mkb.aarhus.dk>
Project-URL: Homepage, https://github.com/itk-dev-rpa/python_serviceplatformen
Project-URL: Bug Tracker, https://github.com/itk-dev-rpa/python_serviceplatformen/issues
Classifier: Programming Language :: Python :: 3
Classifier: License :: OSI Approved :: MIT License
Requires-Python: <3.13,>=3.10
License-File: LICENSE
Requires-Dist: requests==2.*
Requires-Dist: cryptography
Requires-Dist: xmlschema
Requires-Dist: pika==1.3.*
Provides-Extra: dev
Requires-Dist: python-dotenv; extra == "dev"
Requires-Dist: flake8; extra == "dev"
Requires-Dist: pylint; extra == "dev"
Dynamic: license-file
